jinjaconf/__init__.py
jinjaconf/config.py
jinjaconf/render.py
jinjaconf/template.py
jinjaconf/testing.py
jinjaconf-0.1.0.dist-info/METADATA
jinjaconf-0.1.0.dist-info/WHEEL
jinjaconf-0.1.0.dist-info/licenses/LICENSE
jinjaconf-0.1.0.dist-info/RECORD
