Metadata-Version: 2.3
Name: jinjaconf
Version: 0.1.0
Summary: Jinjaconf.
Project-URL: Documentation, https://github.com/daizutabi/jinjaconf
Project-URL: Source, https://github.com/daizutabi/jinjaconf
Project-URL: Issues, https://github.com/daizutabi/jinjaconf/issues
Author-email: daizutabi <daizutabi@gmail.com>
License-Expression: MIT
License-File: LICENSE
Classifier: Development Status :: 4 - Beta
Classifier: Programming Language :: Python
Classifier: Programming Language :: Python :: 3.10
Classifier: Programming Language :: Python :: 3.11
Classifier: Programming Language :: Python :: 3.12
Requires-Python: >=3.10
Requires-Dist: jinja2
Requires-Dist: omegaconf
